{"file:///c%3A/Users/86135/Desktop/CT/projects/dev0.3/util/Pair.java":{"language":"Java","code":35,"comment":0,"blank":9},"file:///c%3A/Users/86135/Desktop/CT/projects/dev0.3/Resourse/config.xml":{"language":"XML","code":149,"comment":10,"blank":10},"file:///c%3A/Users/86135/Desktop/CT/projects/dev0.3/todo_checker.md":{"language":"Markdown","code":48,"comment":0,"blank":12},"file:///c%3A/Users/86135/Desktop/CT/projects/dev0.3/Resourse/ImportStyleCheck.py":{"language":"Python","code":26,"comment":0,"blank":3},"file:///c%3A/Users/86135/Desktop/CT/projects/dev0.3/Resourse/AutoTestJar.py":{"language":"Python","code":40,"comment":2,"blank":3},"file:///c%3A/Users/86135/Desktop/CT/projects/dev0.3/Resourse/AutoMidCompare.py":{"language":"Python","code":55,"comment":6,"blank":4},"file:///c%3A/Users/86135/Desktop/CT/projects/dev0.3/Resourse/AutoMatchTwo.py":{"language":"Python","code":57,"comment":4,"blank":6},"file:///c%3A/Users/86135/Desktop/CT/projects/dev0.3/Resourse/AutoRunJar.py":{"language":"Python","code":28,"comment":1,"blank":3},"file:///c%3A/Users/86135/Desktop/CT/projects/dev0.3/Resourse/AutoCompileTest.py":{"language":"Python","code":49,"comment":3,"blank":3},"file:///c%3A/Users/86135/Desktop/CT/projects/dev0.3/out/production/dev0.2/todo_checker.md":{"language":"Markdown","code":20,"comment":0,"blank":3},"file:///c%3A/Users/86135/Desktop/CT/projects/dev0.3/Resourse/AutoFiltedPacker.py":{"language":"Python","code":31,"comment":0,"blank":5},"file:///c%3A/Users/86135/Desktop/CT/projects/dev0.3/out/production/dev0.1/.idea/misc.xml":{"language":"XML","code":11,"comment":0,"blank":0},"file:///c%3A/Users/86135/Desktop/CT/projects/dev0.3/out/production/dev0.1/.idea/libraries/Mars_2021.xml":{"language":"XML","code":9,"comment":0,"blank":0},"file:///c%3A/Users/86135/Desktop/CT/projects/dev0.3/Resourse/AutoMipsCompare.py":{"language":"Python","code":77,"comment":7,"blank":4},"file:///c%3A/Users/86135/Desktop/CT/projects/dev0.3/out/production/dev0.1/.idea/modules.xml":{"language":"XML","code":8,"comment":0,"blank":0},"file:///c%3A/Users/86135/Desktop/CT/projects/dev0.3/out/production/dev0.1/.idea/checkstyle-idea.xml":{"language":"XML","code":16,"comment":0,"blank":0},"file:///c%3A/Users/86135/Desktop/CT/projects/dev0.3/frontend/tokenize/Reserved.java":{"language":"Java","code":6,"comment":0,"blank":2},"file:///c%3A/Users/86135/Desktop/CT/projects/dev0.3/frontend/tokenize/Token.java":{"language":"Java","code":120,"comment":3,"blank":20},"file:///c%3A/Users/86135/Desktop/CT/projects/dev0.3/frontend/tokenize/Tokenizer.java":{"language":"Java","code":123,"comment":6,"blank":19},"file:///c%3A/Users/86135/Desktop/CT/projects/dev0.3/frontend/tokenize/Ident.java":{"language":"Java","code":9,"comment":0,"blank":4},"file:///c%3A/Users/86135/Desktop/CT/projects/dev0.3/frontend/tokenize/IntConst.java":{"language":"Java","code":12,"comment":0,"blank":5},"file:///c%3A/Users/86135/Desktop/CT/projects/dev0.3/out/production/dev0.2/.idea/vcs.xml":{"language":"XML","code":6,"comment":0,"blank":0},"file:///c%3A/Users/86135/Desktop/CT/projects/dev0.3/frontend/tokenize/FormatStr.java":{"language":"Java","code":15,"comment":0,"blank":5},"file:///c%3A/Users/86135/Desktop/CT/projects/dev0.3/out/production/dev0.2/dev0.2.iml":{"language":"XML","code":22,"comment":0,"blank":0},"file:///c%3A/Users/86135/Desktop/CT/projects/dev0.3/out/production/dev0.2/dev0.1.iml":{"language":"XML","code":22,"comment":0,"blank":0},"file:///c%3A/Users/86135/Desktop/CT/projects/dev0.3/out/production/dev0.2/.idea/misc.xml":{"language":"XML","code":11,"comment":0,"blank":0},"file:///c%3A/Users/86135/Desktop/CT/projects/dev0.3/out/production/dev0.2/.idea/modules.xml":{"language":"XML","code":8,"comment":0,"blank":0},"file:///c%3A/Users/86135/Desktop/CT/projects/dev0.3/out/production/dev0.2/Resourse/ImportStyleCheck.py":{"language":"Python","code":26,"comment":0,"blank":3},"file:///c%3A/Users/86135/Desktop/CT/projects/dev0.3/out/production/dev0.2/Resourse/config.xml":{"language":"XML","code":149,"comment":10,"blank":10},"file:///c%3A/Users/86135/Desktop/CT/projects/dev0.3/out/production/dev0.2/Resourse/AutoTestJar.py":{"language":"Python","code":40,"comment":2,"blank":3},"file:///c%3A/Users/86135/Desktop/CT/projects/dev0.3/out/production/dev0.2/Resourse/AutoRunJar.py":{"language":"Python","code":28,"comment":1,"blank":3},"file:///c%3A/Users/86135/Desktop/CT/projects/dev0.3/out/production/dev0.2/.idea/checkstyle-idea.xml":{"language":"XML","code":16,"comment":0,"blank":0},"file:///c%3A/Users/86135/Desktop/CT/projects/dev0.3/out/production/dev0.2/Resourse/AutoMidCompare.py":{"language":"Python","code":55,"comment":6,"blank":4},"file:///c%3A/Users/86135/Desktop/CT/projects/dev0.3/out/production/dev0.2/Resourse/AutoMipsCompare.py":{"language":"Python","code":77,"comment":7,"blank":4},"file:///c%3A/Users/86135/Desktop/CT/projects/dev0.3/out/production/dev0.2/Resourse/AutoFiltedPacker.py":{"language":"Python","code":31,"comment":0,"blank":5},"file:///c%3A/Users/86135/Desktop/CT/projects/dev0.3/out/production/dev0.2/Resourse/AutoCompileTest.py":{"language":"Python","code":49,"comment":3,"blank":3},"file:///c%3A/Users/86135/Desktop/CT/projects/dev0.3/out/production/dev0.2/Resourse/AutoMatchTwo.py":{"language":"Python","code":47,"comment":3,"blank":3},"file:///c%3A/Users/86135/Desktop/CT/projects/dev0.3/out/production/dev0.2/autotest/AutoMatchTwo.py":{"language":"Python","code":47,"comment":3,"blank":3},"file:///c%3A/Users/86135/Desktop/CT/projects/dev0.3/out/production/dev0.2/.idea/libraries/Mars_20211.xml":{"language":"XML","code":9,"comment":0,"blank":0},"file:///c%3A/Users/86135/Desktop/CT/projects/dev0.3/out/production/dev0.2/.idea/libraries/Mars_2021.xml":{"language":"XML","code":9,"comment":0,"blank":0},"file:///c%3A/Users/86135/Desktop/CT/projects/dev0.3/out/production/dev0.1/Resourse/ImportStyleCheck.py":{"language":"Python","code":26,"comment":0,"blank":3},"file:///c%3A/Users/86135/Desktop/CT/projects/dev0.3/out/production/dev0.2/.idea/artifacts/dev0_2_jar.xml":{"language":"XML","code":8,"comment":0,"blank":0},"file:///c%3A/Users/86135/Desktop/CT/projects/dev0.3/out/production/dev0.1/Resourse/config.xml":{"language":"XML","code":149,"comment":10,"blank":10},"file:///c%3A/Users/86135/Desktop/CT/projects/dev0.3/out/production/dev0.1/Resourse/AutoTestJar.py":{"language":"Python","code":40,"comment":2,"blank":3},"file:///c%3A/Users/86135/Desktop/CT/projects/dev0.3/out/production/dev0.1/Resourse/AutoRunJar.py":{"language":"Python","code":28,"comment":1,"blank":3},"file:///c%3A/Users/86135/Desktop/CT/projects/dev0.3/out/production/dev0.1/Resourse/AutoMipsCompare.py":{"language":"Python","code":77,"comment":7,"blank":4},"file:///c%3A/Users/86135/Desktop/CT/projects/dev0.3/out/production/dev0.1/Resourse/AutoMidCompare.py":{"language":"Python","code":55,"comment":6,"blank":4},"file:///c%3A/Users/86135/Desktop/CT/projects/dev0.3/out/production/dev0.1/Resourse/AutoMatchTwo.py":{"language":"Python","code":47,"comment":3,"blank":3},"file:///c%3A/Users/86135/Desktop/CT/projects/dev0.3/out/production/dev0.1/Resourse/AutoFiltedPacker.py":{"language":"Python","code":31,"comment":0,"blank":5},"file:///c%3A/Users/86135/Desktop/CT/projects/dev0.3/frontend/syntax_design.md":{"language":"Markdown","code":149,"comment":0,"blank":7},"file:///c%3A/Users/86135/Desktop/CT/projects/dev0.3/out/production/dev0.1/Resourse/AutoCompileTest.py":{"language":"Python","code":49,"comment":3,"blank":3},"file:///c%3A/Users/86135/Desktop/CT/projects/dev0.3/driver/Output.java":{"language":"Java","code":35,"comment":0,"blank":11},"file:///c%3A/Users/86135/Desktop/CT/projects/dev0.3/out/production/dev0.1/dev0.1.iml":{"language":"XML","code":22,"comment":0,"blank":0},"file:///c%3A/Users/86135/Desktop/CT/projects/dev0.3/frontend/Source.java":{"language":"Java","code":51,"comment":0,"blank":14},"file:///c%3A/Users/86135/Desktop/CT/projects/dev0.3/driver/Config.java":{"language":"Java","code":102,"comment":2,"blank":17},"file:///c%3A/Users/86135/Desktop/CT/projects/dev0.3/dev0.1.iml":{"language":"XML","code":22,"comment":0,"blank":0},"file:///c%3A/Users/86135/Desktop/CT/projects/dev0.3/dev0.2.iml":{"language":"XML","code":22,"comment":0,"blank":0},"file:///c%3A/Users/86135/Desktop/CT/projects/dev0.3/dev0.3.iml":{"language":"XML","code":22,"comment":0,"blank":0},"file:///c%3A/Users/86135/Desktop/CT/projects/dev0.3/frontend/lang_design.md":{"language":"Markdown","code":162,"comment":0,"blank":20},"file:///c%3A/Users/86135/Desktop/CT/projects/dev0.3/driver/CompilerDriver.java":{"language":"Java","code":31,"comment":2,"blank":6},"file:///c%3A/Users/86135/Desktop/CT/projects/dev0.3/Compiler.java":{"language":"Java","code":12,"comment":0,"blank":4},"file:///c%3A/Users/86135/Desktop/CT/projects/dev0.3/frontend/syntax/TokenNode.java":{"language":"Java","code":14,"comment":0,"blank":6},"file:///c%3A/Users/86135/Desktop/CT/projects/dev0.3/frontend/error/ErrorBuffer.java":{"language":"Java","code":21,"comment":0,"blank":9},"file:///c%3A/Users/86135/Desktop/CT/projects/dev0.3/frontend/error/Error.java":{"language":"Java","code":56,"comment":0,"blank":15},"file:///c%3A/Users/86135/Desktop/CT/projects/dev0.3/frontend/exceptions/TokenTypeNotFoundException.java":{"language":"Java","code":6,"comment":0,"blank":3},"file:///c%3A/Users/86135/Desktop/CT/projects/dev0.3/frontend/syntax/decl/parse/VarDefParser.java":{"language":"Java","code":33,"comment":1,"blank":6},"file:///c%3A/Users/86135/Desktop/CT/projects/dev0.3/frontend/syntax/ParserBase.java":{"language":"Java","code":79,"comment":4,"blank":22},"file:///c%3A/Users/86135/Desktop/CT/projects/dev0.3/frontend/syntax/decl/parse/InitValParser.java":{"language":"Java","code":38,"comment":1,"blank":6},"file:///c%3A/Users/86135/Desktop/CT/projects/dev0.3/frontend/syntax/decl/parse/VarDeclParser.java":{"language":"Java","code":25,"comment":1,"blank":6},"file:///c%3A/Users/86135/Desktop/CT/projects/dev0.3/frontend/syntax/decl/parse/ConstInitValParser.java":{"language":"Java","code":38,"comment":1,"blank":6},"file:///c%3A/Users/86135/Desktop/CT/projects/dev0.3/frontend/syntax/decl/parse/BTypeParser.java":{"language":"Java","code":17,"comment":0,"blank":4},"file:///c%3A/Users/86135/Desktop/CT/projects/dev0.3/frontend/syntax/decl/parse/ConstDeclParser.java":{"language":"Java","code":29,"comment":1,"blank":6},"file:///c%3A/Users/86135/Desktop/CT/projects/dev0.3/frontend/syntax/decl/parse/ConstDefParser.java":{"language":"Java","code":35,"comment":1,"blank":6},"file:///c%3A/Users/86135/Desktop/CT/projects/dev0.3/frontend/syntax/decl/ast/VarDefNode.java":{"language":"Java","code":17,"comment":0,"blank":6},"file:///c%3A/Users/86135/Desktop/CT/projects/dev0.3/frontend/syntax/NodeBase.java":{"language":"Java","code":54,"comment":0,"blank":12},"file:///c%3A/Users/86135/Desktop/CT/projects/dev0.3/frontend/exceptions/FrontendBaseException.java":{"language":"Java","code":9,"comment":0,"blank":3},"file:///c%3A/Users/86135/Desktop/CT/projects/dev0.3/frontend/syntax/decl/ast/VarDeclNode.java":{"language":"Java","code":15,"comment":4,"blank":6},"file:///c%3A/Users/86135/Desktop/CT/projects/dev0.3/frontend/syntax/decl/ast/InitValNode.java":{"language":"Java","code":12,"comment":0,"blank":6},"file:///c%3A/Users/86135/Desktop/CT/projects/dev0.3/frontend/syntax/expr/parse/LValParser.java":{"language":"Java","code":28,"comment":1,"blank":7},"file:///c%3A/Users/86135/Desktop/CT/projects/dev0.3/frontend/syntax/expr/parse/LAndExpParser.java":{"language":"Java","code":24,"comment":1,"blank":8},"file:///c%3A/Users/86135/Desktop/CT/projects/dev0.3/frontend/syntax/expr/parse/FuncRParamsParser.java":{"language":"Java","code":20,"comment":0,"blank":6},"file:///c%3A/Users/86135/Desktop/CT/projects/dev0.3/frontend/syntax/expr/ast/UnaryExpNode.java":{"language":"Java","code":13,"comment":0,"blank":5},"file:///c%3A/Users/86135/Desktop/CT/projects/dev0.3/frontend/syntax/expr/parse/LOrExpParser.java":{"language":"Java","code":24,"comment":1,"blank":8},"file:///c%3A/Users/86135/Desktop/CT/projects/dev0.3/frontend/syntax/expr/ast/LValNode.java":{"language":"Java","code":15,"comment":1,"blank":6},"file:///c%3A/Users/86135/Desktop/CT/projects/dev0.3/frontend/syntax/expr/parse/NumberParser.java":{"language":"Java","code":18,"comment":1,"blank":5},"file:///c%3A/Users/86135/Desktop/CT/projects/dev0.3/frontend/syntax/expr/parse/ExpParser.java":{"language":"Java","code":12,"comment":1,"blank":3},"file:///c%3A/Users/86135/Desktop/CT/projects/dev0.3/frontend/syntax/expr/parse/EqExpParser.java":{"language":"Java","code":24,"comment":1,"blank":8},"file:///c%3A/Users/86135/Desktop/CT/projects/dev0.3/frontend/syntax/expr/ast/FuncRParamsNode.java":{"language":"Java","code":12,"comment":1,"blank":5},"file:///c%3A/Users/86135/Desktop/CT/projects/dev0.3/frontend/syntax/expr/parse/MulExpParser.java":{"language":"Java","code":24,"comment":2,"blank":8},"file:///c%3A/Users/86135/Desktop/CT/projects/dev0.3/frontend/syntax/expr/ast/FuncCallNode.java":{"language":"Java","code":14,"comment":1,"blank":5},"file:///c%3A/Users/86135/Desktop/CT/projects/dev0.3/frontend/syntax/expr/ast/BinaryExpNode.java":{"language":"Java","code":17,"comment":2,"blank":6},"file:///c%3A/Users/86135/Desktop/CT/projects/dev0.3/frontend/syntax/expr/parse/CondParser.java":{"language":"Java","code":11,"comment":1,"blank":4},"file:///c%3A/Users/86135/Desktop/CT/projects/dev0.3/frontend/syntax/expr/parse/ConstExpParser.java":{"language":"Java","code":11,"comment":1,"blank":4},"file:///c%3A/Users/86135/Desktop/CT/projects/dev0.3/frontend/syntax/expr/parse/UnaryOpParser.java":{"language":"Java","code":18,"comment":0,"blank":6},"file:///c%3A/Users/86135/Desktop/CT/projects/dev0.3/frontend/syntax/expr/parse/PrimaryExpParser.java":{"language":"Java","code":26,"comment":1,"blank":5},"file:///c%3A/Users/86135/Desktop/CT/projects/dev0.3/frontend/syntax/expr/parse/AddExpParser.java":{"language":"Java","code":24,"comment":1,"blank":8},"file:///c%3A/Users/86135/Desktop/CT/projects/dev0.3/frontend/syntax/expr/parse/RelExpParser.java":{"language":"Java","code":24,"comment":1,"blank":8},"file:///c%3A/Users/86135/Desktop/CT/projects/dev0.3/frontend/syntax/expr/parse/UnaryExpParser.java":{"language":"Java","code":50,"comment":1,"blank":9},"file:///c%3A/Users/86135/Desktop/CT/projects/dev0.3/frontend/syntax/func/parse/FuncTypeParser.java":{"language":"Java","code":14,"comment":1,"blank":4},"file:///c%3A/Users/86135/Desktop/CT/projects/dev0.3/frontend/syntax/func/parse/FuncDefParser.java":{"language":"Java","code":26,"comment":1,"blank":4},"file:///c%3A/Users/86135/Desktop/CT/projects/dev0.3/frontend/syntax/func/parse/FuncFParamParser.java":{"language":"Java","code":28,"comment":1,"blank":4},"file:///c%3A/Users/86135/Desktop/CT/projects/dev0.3/frontend/syntax/stmt/ast/AssignNode.java":{"language":"Java","code":13,"comment":0,"blank":5},"file:///c%3A/Users/86135/Desktop/CT/projects/dev0.3/frontend/syntax/func/parse/FuncFParamsParser.java":{"language":"Java","code":14,"comment":1,"blank":4},"file:///c%3A/Users/86135/Desktop/CT/projects/dev0.3/frontend/syntax/stmt/ast/BlockNode.java":{"language":"Java","code":11,"comment":0,"blank":5},"file:///c%3A/Users/86135/Desktop/CT/projects/dev0.3/frontend/syntax/stmt/ast/PrintNode.java":{"language":"Java","code":15,"comment":0,"blank":6},"file:///c%3A/Users/86135/Desktop/CT/projects/dev0.3/frontend/syntax/stmt/ast/ReturnNode.java":{"language":"Java","code":11,"comment":0,"blank":5},"file:///c%3A/Users/86135/Desktop/CT/projects/dev0.3/frontend/syntax/stmt/ast/LoopNode.java":{"language":"Java","code":13,"comment":0,"blank":5},"file:///c%3A/Users/86135/Desktop/CT/projects/dev0.3/out/production/dev0.2/frontend/lang_design.md":{"language":"Markdown","code":107,"comment":0,"blank":5},"file:///c%3A/Users/86135/Desktop/CT/projects/dev0.3/frontend/syntax/stmt/ast/GetintNode.java":{"language":"Java","code":11,"comment":0,"blank":5},"file:///c%3A/Users/86135/Desktop/CT/projects/dev0.3/frontend/syntax/stmt/ast/ContinueNode.java":{"language":"Java","code":7,"comment":0,"blank":3},"file:///c%3A/Users/86135/Desktop/CT/projects/dev0.3/frontend/syntax/stmt/ast/ConditionNode.java":{"language":"Java","code":16,"comment":0,"blank":5},"file:///c%3A/Users/86135/Desktop/CT/projects/dev0.3/frontend/syntax/stmt/ast/BreakNode.java":{"language":"Java","code":7,"comment":0,"blank":3},"file:///c%3A/Users/86135/Desktop/CT/projects/dev0.3/frontend/syntax/func/parse/MainFuncDefParser.java":{"language":"Java","code":25,"comment":1,"blank":4},"file:///c%3A/Users/86135/Desktop/CT/projects/dev0.3/frontend/syntax/stmt/parser/StmtParser.java":{"language":"Java","code":168,"comment":13,"blank":11},"file:///c%3A/Users/86135/Desktop/CT/projects/dev0.3/.idea/uiDesigner.xml":{"language":"XML","code":124,"comment":0,"blank":0},"file:///c%3A/Users/86135/Desktop/CT/projects/dev0.3/.idea/checkstyle-idea.xml":{"language":"XML","code":16,"comment":0,"blank":0},"file:///c%3A/Users/86135/Desktop/CT/projects/dev0.3/.idea/vcs.xml":{"language":"XML","code":6,"comment":0,"blank":0},"file:///c%3A/Users/86135/Desktop/CT/projects/dev0.3/frontend/syntax/stmt/parser/BlockParser.java":{"language":"Java","code":35,"comment":1,"blank":4},"file:///c%3A/Users/86135/Desktop/CT/projects/dev0.3/.idea/misc.xml":{"language":"XML","code":11,"comment":0,"blank":0},"file:///c%3A/Users/86135/Desktop/CT/projects/dev0.3/.idea/modules.xml":{"language":"XML","code":8,"comment":0,"blank":0},"file:///c%3A/Users/86135/Desktop/CT/projects/dev0.3/.idea/libraries/Mars_20212.xml":{"language":"XML","code":9,"comment":0,"blank":0},"file:///c%3A/Users/86135/Desktop/CT/projects/dev0.3/.idea/libraries/Mars_2021.xml":{"language":"XML","code":9,"comment":0,"blank":0},"file:///c%3A/Users/86135/Desktop/CT/projects/dev0.3/.idea/libraries/Mars_20211.xml":{"language":"XML","code":9,"comment":0,"blank":0},"file:///c%3A/Users/86135/Desktop/CT/projects/dev0.3/.idea/libraries/autotest.xml":{"language":"XML","code":11,"comment":0,"blank":0},"file:///c%3A/Users/86135/Desktop/CT/projects/dev0.3/.idea/libraries/dev0_2.xml":{"language":"XML","code":9,"comment":0,"blank":0},"file:///c%3A/Users/86135/Desktop/CT/projects/dev0.3/.idea/libraries/Compiler_21_dhy.xml":{"language":"XML","code":9,"comment":0,"blank":0},"file:///c%3A/Users/86135/Desktop/CT/projects/dev0.3/autotest/AutoMatchTwo.py":{"language":"Python","code":65,"comment":4,"blank":6},"file:///c%3A/Users/86135/Desktop/CT/projects/dev0.3/frontend/syntax/CompUnitParser.java":{"language":"Java","code":51,"comment":1,"blank":4}}